{
  "db_name": "PostgreSQL",
  "query": "SELECT device_code_sha256 AS \"device_code_sha256!: Vec<u8>\" FROM device_auth_sessions\n               WHERE user_code = $1 AND intent IN ('enroll', 'login') AND status IN ('pending', 'confirmed') LIMIT 1",
  "describe": {
    "columns": [
      {
        "ordinal": 0,
        "name": "device_code_sha256!: Vec<u8>",
        "type_info": "Bytea"
      }
    ],
    "parameters": {
      "Left": [
        "Text"
      ]
    },
    "nullable": [
      false
    ]
  },
  "hash": "c43725ae66212bca6d4547263acccbc59c69de1e51a2aa65ea49434446385552"
}
