{
  "db_name": "PostgreSQL",
  "query": "SELECT wm.workspace_id AS \"workspace_id!\", wm.role AS \"role!\",\n                  w.name AS \"name!\", w.display_name AS \"display_name!\"\n           FROM workspace_member wm\n           JOIN workspace w ON w.workspace_id = wm.workspace_id\n           WHERE wm.principal = $1 AND wm.status = 'confirmed'\n           ORDER BY wm.workspace_id",
  "describe": {
    "columns": [
      {
        "ordinal": 0,
        "name": "workspace_id!",
        "type_info": "Text"
      },
      {
        "ordinal": 1,
        "name": "role!",
        "type_info": "Text"
      },
      {
        "ordinal": 2,
        "name": "name!",
        "type_info": "Text"
      },
      {
        "ordinal": 3,
        "name": "display_name!",
        "type_info": "Text"
      }
    ],
    "parameters": {
      "Left": [
        "Text"
      ]
    },
    "nullable": [
      false,
      false,
      false,
      false
    ]
  },
  "hash": "656f360232c15778c55e896953197a61aed91d0b9a241c3ae6733b5a31a3ee2a"
}
